tracking_data/__init__.py
tracking_data/dataset.py
tracking_data/dataset_error.py
tracking_data/datarow/__init__.py
tracking_data/datarow/annotation.py
tracking_data/datarow/datarow.py
tracking_data/datarow/datarow_error.py
tracking_data-0.0.17.dist-info/METADATA
tracking_data-0.0.17.dist-info/WHEEL
tracking_data-0.0.17.dist-info/top_level.txt
tracking_data-0.0.17.dist-info/RECORD
