Metadata-Version: 2.1
Name: tracking-data
Version: 0.0.17
Summary: Tracking annotated data package
Author: Rodion Shyshkin
Author-email: <rodion.shyshkin@gmail.com>
License: UNKNOWN
Keywords: python,tracking,datasets
Platform: UNKNOWN
Classifier: Development Status :: 3 - Alpha
Classifier: Intended Audience :: Education
Classifier: Programming Language :: Python :: 2
Classifier: Programming Language :: Python :: 3
Classifier: Operating System :: MacOS :: MacOS X
Classifier: Operating System :: Microsoft :: Windows
Requires-Dist: opencv-contrib-python
